odoo/addons/stock_vertical_lift_server_env/README.rst
odoo/addons/stock_vertical_lift_server_env/__init__.py
odoo/addons/stock_vertical_lift_server_env/__manifest__.py
odoo/addons/stock_vertical_lift_server_env/i18n/it.po
odoo/addons/stock_vertical_lift_server_env/i18n/stock_vertical_lift_server_env.pot
odoo/addons/stock_vertical_lift_server_env/models/__init__.py
odoo/addons/stock_vertical_lift_server_env/models/vertical_lift_shuttle.py
odoo/addons/stock_vertical_lift_server_env/readme/CONTRIBUTORS.md
odoo/addons/stock_vertical_lift_server_env/readme/DESCRIPTION.md
odoo/addons/stock_vertical_lift_server_env/static/description/icon.png
odoo/addons/stock_vertical_lift_server_env/static/description/index.html
odoo_addon_stock_vertical_lift_server_env-18.0.1.0.0.3.dist-info/METADATA
odoo_addon_stock_vertical_lift_server_env-18.0.1.0.0.3.dist-info/WHEEL
odoo_addon_stock_vertical_lift_server_env-18.0.1.0.0.3.dist-info/top_level.txt
odoo_addon_stock_vertical_lift_server_env-18.0.1.0.0.3.dist-info/RECORD
